hictkpy/__init__.py
hictkpy/_hictkpy.cp310-win_amd64.pyd
hictkpy-1.4.0.dist-info/METADATA
hictkpy-1.4.0.dist-info/WHEEL
hictkpy-1.4.0.dist-info/licenses/LICENSE
hictkpy-1.4.0.dist-info/licenses/external/licenses/hictk.LICENSE
hictkpy-1.4.0.dist-info/licenses/external/licenses/nanobind.LICENSE
hictkpy-1.4.0.dist-info/licenses/external/licenses/project_options.LICENSE.txt
hictkpy-1.4.0.dist-info/RECORD
