Metadata-Version: 2.4
Name: hictkpy
Version: 1.4.0
Summary: Python bindings for hictk: read and write .cool and .hic files directly from Python
Author-Email: Roberto Rossini <roberros@uio.no>
License-Expression: MIT
License-File: external/licenses/hictk.LICENSE
License-File: external/licenses/nanobind.LICENSE
License-File: external/licenses/project_options.LICENSE.txt
License-File: LICENSE
Classifier: Programming Language :: Python :: 3 :: Only
Classifier: Programming Language :: Python :: 3.10
Classifier: Programming Language :: Python :: 3.11
Classifier: Programming Language :: Python :: 3.12
Classifier: Programming Language :: Python :: 3.13
Classifier: Programming Language :: Python :: 3.14
Classifier: Programming Language :: Python :: Free Threading :: 1 - Unstable
Classifier: Topic :: Scientific/Engineering :: Bio-Informatics
Requires-Python: >=3.10
Provides-Extra: numpy
Requires-Dist: numpy; extra == "numpy"
Provides-Extra: pandas
Requires-Dist: hictkpy[pyarrow]; extra == "pandas"
Requires-Dist: pandas!=2.2.0,>=2.1.0; extra == "pandas"
Provides-Extra: pyarrow
Requires-Dist: pyarrow>=16; extra == "pyarrow"
Provides-Extra: scipy
Requires-Dist: scipy; extra == "scipy"
Provides-Extra: all
Requires-Dist: hictkpy[numpy,pandas,pyarrow,scipy]; extra == "all"
